README.md
pyproject.toml
setup.py
dkdisc/__init__.py
dkdisc/dkdisc.py
dkdisc.egg-info/PKG-INFO
dkdisc.egg-info/SOURCES.txt
dkdisc.egg-info/dependency_links.txt
dkdisc.egg-info/entry_points.txt
dkdisc.egg-info/top_level.txt
dkdisc/finitediff/__init__.py
dkdisc/finitediff/grid.py
dkdisc/finitediff/linear.py
dkdisc/finitediff/nonlinear.py
dkdisc/utils/__init__.py
dkdisc/utils/encoders.py
dkdisc/utils/experiment.py
dkdisc/utils/output.py
dkdisc/utils/plotting.py