Metadata-Version: 2.1
Name: dkdisc
Version: 0.1.0rc9
Summary: Collection of solvers for Dean-Kawasaki
Home-page: https://github.com/qwinters/dean-kawasaki-discretizations
Author: Fischer Group
Requires-Python: >=3.6
